CHANGES.rst
LICENSE
MANIFEST.in
README.rst
setup.cfg
setup.py
ddd_nginx/__init__.py
ddd_nginx/__version__.py
ddd_nginx/block.py
ddd_nginx/file_manager.py
ddd_nginx/location.py
ddd_nginx/map.py
ddd_nginx/nginx.py
ddd_nginx/server.py
ddd_nginx/upstream.py
ddd_nginx.egg-info/PKG-INFO
ddd_nginx.egg-info/SOURCES.txt
ddd_nginx.egg-info/dependency_links.txt
ddd_nginx.egg-info/requires.txt
ddd_nginx.egg-info/top_level.txt
ddd_nginx/exception/__init__.py
ddd_nginx/exception/location_error.py
ddd_nginx/exception/nginx_base_exception.py
ddd_nginx/exception/nginx_error.py
ddd_nginx/exception/server_error.py
ddd_nginx/template/__init__.py
ddd_nginx/template/apigw/__init__.py
ddd_nginx/template/apigw/all-in-one.conf.jinja2
ddd_nginx/template/apigw/error_page.conf
ddd_nginx/template/apigw/location-proxy.conf.jinja2
ddd_nginx/template/apigw/location-rewrite.conf.jinja2
ddd_nginx/template/apigw/location.conf.jinja2
ddd_nginx/template/apigw/map.conf.jinja2
ddd_nginx/template/apigw/nginx.conf.jinja2
ddd_nginx/template/apigw/server.conf.jinja2
ddd_nginx/template/apigw/upstream.conf.jinja2
requirements/base.txt
requirements/ci.txt
requirements/test.txt
requirements/tox.txt